LICENSE
MANIFEST.in
README.rst
setup.py
tests/test_config.py
tests/test_errors.py
tests/test_usage.py
xl2thrift/__init__.py
xl2thrift/command_line.py
xl2thrift/exceptions.py
xl2thrift/mutate.py
xl2thrift/mutate_cmd.py
xl2thrift/thriftExcelTools.py
xl2thrift/validate.py
xl2thrift/validate_cmd.py
xl2thrift.egg-info/PKG-INFO
xl2thrift.egg-info/SOURCES.txt
xl2thrift.egg-info/dependency_links.txt
xl2thrift.egg-info/entry_points.txt
xl2thrift.egg-info/not-zip-safe
xl2thrift.egg-info/requires.txt
xl2thrift.egg-info/top_level.txt